Metadata-Version: 2.1
Name: cuschecker
Version: 0.0.1
Summary: Checks for swear words
Home-page: UNKNOWN
Author: Yassa Taiseer
Author-email: yassataiseer@gmail.com
License: MIT
Keywords: calculator
Platform: UNKNOWN
Classifier: Development Status :: 5 - Production/Stable
Classifier: Intended Audience :: Education
Classifier: License :: OSI Approved :: MIT License
Classifier: Programming Language :: Python :: 3
License-File: LICENCE.txt
